framegrab_mcp_server.py
framegrab_mcp_server-0.1.3.dist-info/METADATA
framegrab_mcp_server-0.1.3.dist-info/WHEEL
framegrab_mcp_server-0.1.3.dist-info/entry_points.txt
framegrab_mcp_server-0.1.3.dist-info/licenses/LICENSE
framegrab_mcp_server-0.1.3.dist-info/RECORD
