Metadata-Version: 2.4
Name: framegrab-mcp-server
Version: 0.1.3
Summary: Allow LLMs to capture images from cameras and video streams.
Author: Groundlight AI
License: Apache-2.0
License-File: LICENSE
Classifier: Development Status :: 4 - Beta
Classifier: Intended Audience :: Developers
Classifier: Intended Audience :: End Users/Desktop
Classifier: Intended Audience :: Information Technology
Classifier: Intended Audience :: Science/Research
Classifier: License :: OSI Approved :: Apache Software License
Classifier: Natural Language :: English
Classifier: Operating System :: OS Independent
Classifier: Programming Language :: Python
Classifier: Programming Language :: Python :: 3
Classifier: Programming Language :: Python :: 3.10
Classifier: Programming Language :: Python :: 3.11
Classifier: Programming Language :: Python :: 3.12
Classifier: Topic :: Multimedia :: Video :: Capture
Classifier: Topic :: Software Development :: Libraries
Classifier: Topic :: Utilities
Requires-Python: >=3.10
Requires-Dist: framegrab>=0.11.1
Requires-Dist: mcp[cli]
Requires-Dist: pypylon
Requires-Dist: streamlink
Provides-Extra: dev
Requires-Dist: ruff>=0.7.3; extra == 'dev'
